Metadata-Version: 1.0
Name: NearPy
Version: 0.2
Summary: Framework for fast approximated nearest neighbour search.
Home-page: http://pypi.python.org/pypi/NearPy/
Author: Ole Krause-Sparmann
Author-email: ole@pixelogik.de
License: LICENSE.txt
Platform: UNKNOWN
